{
  "timestamp": "2022-08-08T03:48:48.407Z",
  "reports": [
    {
      "url": "https://mazipan.space/",
      "device": "mobile",
      "perf": 0.64,
      "fid": 17,
      "lcp": 2676,
      "cls": 0.00153,
      "fcp": 2490,
      "fci": 0,
      "tbt": 1162.5,
      "tti": 7325.5,
      "si": 2937.85,
      "req": 60,
      "size": 537612
    },
    {
      "url": "https://mazipan.space/",
      "device": "desktop",
      "perf": 0.95,
      "fid": 4,
      "lcp": 1441,
      "cls": 0.01594,
      "fcp": 755.5,
      "fci": 0,
      "tbt": 7,
      "tti": 1263,
      "si": 780.36,
      "req": 74,
      "size": 720048
    }
  ]
}